rust_pypi-1.10.0.dist-info/WHEEL
rust_pypi-1.10.0.dist-info/top_level.txt
rust_pypi-1.10.0.dist-info/METADATA
rust_pypi-1.10.0.dist-info/RECORD
rust_pypi/rust_pypi.so
rust_pypi/double.py
rust_pypi/__init__.py
rust_pypi/version.py
